mcmctoolbox/__init__.py
mcmctoolbox/func.py
mcmctoolbox/kernel.py
mcmctoolbox/mcmc.py
mcmctoolbox-0.21.0.dist-info/METADATA
mcmctoolbox-0.21.0.dist-info/WHEEL
mcmctoolbox-0.21.0.dist-info/licenses/LICENSE
mcmctoolbox-0.21.0.dist-info/RECORD
