Metadata-Version: 2.4
Name: mcmctoolbox
Version: 0.21.0
Summary: MCMC Algorithms
License-File: LICENSE
Requires-Python: >=3.10
Requires-Dist: jax>=0.4.38
Requires-Dist: jaxtyping>=0.2.36
Requires-Dist: matplotlib>=3.10.0
Requires-Dist: scipy>=1.14.1
Requires-Dist: seaborn>=0.13.2
Requires-Dist: sphinx-autodoc-typehints>=2.5.0
Requires-Dist: sphinx-markdown-builder>=0.6.7
Requires-Dist: sphinx-rtd-theme>=3.0.2
Requires-Dist: sphinx>=8.1.3
Requires-Dist: stein-thinning>=0.2.0
Requires-Dist: tqdm>=4.67.1
